sip_client/__init__.py
sip_client/pj/__init__.py
sip_client/pj/sip_client.py
sip_client/udp/__init__.py
sip_client/udp/call.py
sip_client/udp/call_fsm.py
sip_client/udp/sip_client.py
sip_client/udp/utils.py
nx_sip_client-1.0.2.dist-info/LICENSE
nx_sip_client-1.0.2.dist-info/METADATA
nx_sip_client-1.0.2.dist-info/WHEEL
nx_sip_client-1.0.2.dist-info/top_level.txt
nx_sip_client-1.0.2.dist-info/RECORD
