Metadata-Version: 2.1
Name: nx-sip-client
Version: 1.0.2
Summary: Python SIP client library with PJSUA2 and native UDP implementations
Author-email: William Wu <science.william@gmail.com>
Maintainer-email: William Wu <science.william@gmail.com>
License: MIT
Project-URL: Homepage, https://github.com/nexuni/sip-client
Project-URL: Documentation, https://github.com/nexuni/sip-client#readme
Project-URL: Repository, https://github.com/nexuni/sip-client.git
Project-URL: Bug Tracker, https://github.com/nexuni/sip-client/issues
Project-URL: Changelog, https://github.com/nexuni/sip-client/releases
Keywords: sip,voip,pjsua2,udp,telephony,rtp,audio,communication
Classifier: Development Status :: 3 - Alpha
Classifier: Intended Audience :: Developers
Classifier: License :: OSI Approved :: MIT License
Classifier: Operating System :: OS Independent
Classifier: Programming Language :: Python :: 3
Classifier: Programming Language :: Python :: 3.8
Classifier: Programming Language :: Python :: 3.9
Classifier: Programming Language :: Python :: 3.10
Classifier: Programming Language :: Python :: 3.11
Classifier: Topic :: Communications :: Telephony
Classifier: Topic :: Software Development :: Libraries :: Python Modules
Classifier: Topic :: System :: Networking
Requires-Python: >=3.8
License-File: LICENSE
Provides-Extra: audio
Requires-Dist: pyaudio; extra == "audio"
Requires-Dist: sounddevice; extra == "audio"
Requires-Dist: soundfile; extra == "audio"
Provides-Extra: pjsua2
